README.md
setup.py
taobao_openapi.egg-info/PKG-INFO
taobao_openapi.egg-info/SOURCES.txt
taobao_openapi.egg-info/dependency_links.txt
taobao_openapi.egg-info/requires.txt
taobao_openapi.egg-info/top_level.txt
top/__init__.py
top/api/__init__.py
top/api/base.py
top/api/rest/AppipGetRequest.py
top/api/rest/AppstoreSubscribeGetRequest.py
top/api/rest/AreasGetRequest.py
top/api/rest/CainiaoCbossWorkplatformBiztypeQueryallRequest.py
top/api/rest/CainiaoCbossWorkplatformBiztypeQuerybyidRequest.py
top/api/rest/CainiaoCbossWorkplatformLogisticsIscainiaoorderRequest.py
top/api/rest/CainiaoCbossWorkplatformOperationReplyRequest.py
top/api/rest/CainiaoCbossWorkplatformWorkorderCreateRequest.py
top/api/rest/CainiaoCbossWorkplatformWorkorderProcessNotifyRequest.py
top/api/rest/CainiaoCbossWorkplatformWorkorderTaskNotifyRequest.py
top/api/rest/DeliveryTemplateAddRequest.py
top/api/rest/DeliveryTemplateDeleteRequest.py
top/api/rest/DeliveryTemplateGetRequest.py
top/api/rest/DeliveryTemplateUpdateRequest.py
top/api/rest/DeliveryTemplatesGetRequest.py
top/api/rest/FilesGetRequest.py
top/api/rest/FuwuSaleLinkGenRequest.py
top/api/rest/FuwuScoresGetRequest.py
top/api/rest/HttpdnsGetRequest.py
top/api/rest/ItemSkuGetRequest.py
top/api/rest/ItemSkusGetRequest.py
top/api/rest/ItemcatsAuthorizeGetRequest.py
top/api/rest/ItemsCustomGetRequest.py
top/api/rest/ItemsInventoryGetRequest.py
top/api/rest/ItemsOnsaleGetRequest.py
top/api/rest/JushitaJdpUserAddRequest.py
top/api/rest/JushitaJdpUserDeleteRequest.py
top/api/rest/JushitaJdpUsersGetRequest.py
top/api/rest/KfcKeywordSearchRequest.py
top/api/rest/LogisticsAddressAddRequest.py
top/api/rest/LogisticsAddressModifyRequest.py
top/api/rest/LogisticsAddressReachableRequest.py
top/api/rest/LogisticsAddressReachablebatchGetRequest.py
top/api/rest/LogisticsAddressRemoveRequest.py
top/api/rest/LogisticsAddressSearchRequest.py
top/api/rest/LogisticsCompaniesGetRequest.py
top/api/rest/LogisticsConsignResendRequest.py
top/api/rest/LogisticsOrdersDetailGetRequest.py
top/api/rest/LogisticsOrdersGetRequest.py
top/api/rest/LogisticsPartnersGetRequest.py
top/api/rest/LogisticsTraceSearchRequest.py
